ms_tools/__init__.py
ms_tools/composition.py
ms_tools/viz.py
ms_tools-0.2.1.dist-info/LICENSE
ms_tools-0.2.1.dist-info/METADATA
ms_tools-0.2.1.dist-info/WHEEL
ms_tools-0.2.1.dist-info/top_level.txt
ms_tools-0.2.1.dist-info/RECORD
