Metadata-Version: 2.1
Name: ms-tools
Version: 0.2.1
Summary: Functions that I commonly use
Home-page: UNKNOWN
Author: michaelsilverstein
Author-email: michael.silverstein4@gmail.com
License: MIT
Platform: UNKNOWN
Requires-Dist: numpy
Requires-Dist: pandas
Requires-Dist: scikit-bio
